.gitignore
LICENSE.txt
README.rst
setup.py
tox.ini
docs/api.rst
docs/conf.py
docs/index.rst
docs/quickstart.rst
src/channel_access.common.egg-info/PKG-INFO
src/channel_access.common.egg-info/SOURCES.txt
src/channel_access.common.egg-info/dependency_links.txt
src/channel_access.common.egg-info/requires.txt
src/channel_access.common.egg-info/top_level.txt
src/channel_access/common/__init__.py
src/channel_access/common/flag.py
src/channel_access/common/ca/ca.cpp
tests/__init__.py
tests/test_flag.py
tests/test_timestamp.py