Metadata-Version: 2.1
Name: channel-access.common
Version: 0.1.0
Summary: Channel Access common library
Home-page: UNKNOWN
Author: André Althaus
Author-email: andre.althaus@tu-dortmund.de
License: MIT
Keywords: epics ca channel_access
Platform: UNKNOWN
Classifier: Development Status :: 3 - Alpha
Classifier: License :: OSI Approved :: MIT License
Classifier: Programming Language :: Python :: 3
Classifier: Programming Language :: Python :: 3.5
Classifier: Programming Language :: Python :: 3.6
Classifier: Programming Language :: Python :: 3.7
Classifier: Topic :: Scientific/Engineering
Requires-Python: >= 3.5
Provides-Extra: doc
Provides-Extra: dev
Provides-Extra: test
